[
  {
    "rank": "1",
    "movieName": "Nope",
    "link": "https://www.imdb.com/title/tt10954984/?ref_=adv_li_tt"
  },
  {
    "rank": "2",
    "movieName": "Samaritan",
    "link": "https://www.imdb.com/title/tt5500218/?ref_=adv_li_tt"
  },
  {
    "rank": "3",
    "movieName": "Top Gun: Maverick",
    "link": "https://www.imdb.com/title/tt1745960/?ref_=adv_li_tt"
  },
  {
    "rank": "4",
    "movieName": "Me Time",
    "link": "https://www.imdb.com/title/tt14309446/?ref_=adv_li_tt"
  },
  {
    "rank": "5",
    "movieName": "Bullet Train",
    "link": "https://www.imdb.com/title/tt12593682/?ref_=adv_li_tt"
  },
  {
    "rank": "6",
    "movieName": "Fall",
    "link": "https://www.imdb.com/title/tt15325794/?ref_=adv_li_tt"
  },
  {
    "rank": "7",
    "movieName": "Elvis",
    "link": "https://www.imdb.com/title/tt3704428/?ref_=adv_li_tt"
  },
  {
    "rank": "8",
    "movieName": "Prey",
    "link": "https://www.imdb.com/title/tt11866324/?ref_=adv_li_tt"
  },
  {
    "rank": "9",
    "movieName": "I Came By",
    "link": "https://www.imdb.com/title/tt15083184/?ref_=adv_li_tt"
  },
  {
    "rank": "10",
    "movieName": "The Invitation",
    "link": "https://www.imdb.com/title/tt12873562/?ref_=adv_li_tt"
  },
  {
    "rank": "11",
    "movieName": "Orphan: First Kill",
    "link": "https://www.imdb.com/title/tt11851548/?ref_=adv_li_tt"
  },
  {
    "rank": "12",
    "movieName": "Three Thousand Years of Longing",
    "link": "https://www.imdb.com/title/tt9198364/?ref_=adv_li_tt"
  },
  {
    "rank": "13",
    "movieName": "Day Shift",
    "link": "https://www.imdb.com/title/tt13314558/?ref_=adv_li_tt"
  },
  {
    "rank": "14",
    "movieName": "Weird: The Al Yankovic Story",
    "link": "https://www.imdb.com/title/tt17076046/?ref_=adv_li_tt"
  },
  {
    "rank": "15",
    "movieName": "Pinocchio",
    "link": "https://www.imdb.com/title/tt4593060/?ref_=adv_li_tt"
  },
  {
    "rank": "16",
    "movieName": "Don't Worry Darling",
    "link": "https://www.imdb.com/title/tt10731256/?ref_=adv_li_tt"
  },
  {
    "rank": "17",
    "movieName": "Look Both Ways",
    "link": "https://www.imdb.com/title/tt14298328/?ref_=adv_li_tt"
  },
  {
    "rank": "18",
    "movieName": "Beast",
    "link": "https://www.imdb.com/title/tt13223398/?ref_=adv_li_tt"
  },
  {
    "rank": "19",
    "movieName": "The Gray Man",
    "link": "https://www.imdb.com/title/tt1649418/?ref_=adv_li_tt"
  },
  {
    "rank": "20",
    "movieName": "Where the Crawdads Sing",
    "link": "https://www.imdb.com/title/tt9411972/?ref_=adv_li_tt"
  },
  {
    "rank": "21",
    "movieName": "DC League of Super-Pets",
    "link": "https://www.imdb.com/title/tt8912936/?ref_=adv_li_tt"
  },
  {
    "rank": "22",
    "movieName": "Everything Everywhere All at Once",
    "link": "https://www.imdb.com/title/tt6710474/?ref_=adv_li_tt"
  },
  {
    "rank": "23",
    "movieName": "Loving Adults",
    "link": "https://www.imdb.com/title/tt14592948/?ref_=adv_li_tt"
  },
  {
    "rank": "24",
    "movieName": "Thor: Love and Thunder",
    "link": "https://www.imdb.com/title/tt10648342/?ref_=adv_li_tt"
  },
  {
    "rank": "25",
    "movieName": "Thirteen Lives",
    "link": "https://www.imdb.com/title/tt12262116/?ref_=adv_li_tt"
  },
  {
    "rank": "26",
    "movieName": "Jurassic World Dominion",
    "link": "https://www.imdb.com/title/tt8041270/?ref_=adv_li_tt"
  },
  {
    "rank": "27",
    "movieName": "X",
    "link": "https://www.imdb.com/title/tt13560574/?ref_=adv_li_tt"
  },
  {
    "rank": "28",
    "movieName": "Dragon Ball Super: Super Hero",
    "link": "https://www.imdb.com/title/tt14614892/?ref_=adv_li_tt"
  },
  {
    "rank": "29",
    "movieName": "Love in the Villa",
    "link": "https://www.imdb.com/title/tt15463032/?ref_=adv_li_tt"
  },
  {
    "rank": "30",
    "movieName": "Liger",
    "link": "https://www.imdb.com/title/tt4435072/?ref_=adv_li_tt"
  },
  {
    "rank": "31",
    "movieName": "Uncharted",
    "link": "https://www.imdb.com/title/tt1464335/?ref_=adv_li_tt"
  },
  {
    "rank": "32",
    "movieName": "The Batman",
    "link": "https://www.imdb.com/title/tt1877830/?ref_=adv_li_tt"
  },
  {
    "rank": "33",
    "movieName": "White Noise",
    "link": "https://www.imdb.com/title/tt6160448/?ref_=adv_li_tt"
  },
  {
    "rank": "34",
    "movieName": "Hit: The First Case",
    "link": "https://www.imdb.com/title/tt13130760/?ref_=adv_li_tt"
  },
  {
    "rank": "35",
    "movieName": "The Northman",
    "link": "https://www.imdb.com/title/tt11138512/?ref_=adv_li_tt"
  },
  {
    "rank": "36",
    "movieName": "The Lost City",
    "link": "https://www.imdb.com/title/tt13320622/?ref_=adv_li_tt"
  },
  {
    "rank": "37",
    "movieName": "After Ever Happy",
    "link": "https://www.imdb.com/title/tt13070038/?ref_=adv_li_tt"
  },
  {
    "rank": "38",
    "movieName": "Blonde",
    "link": "https://www.imdb.com/title/tt1655389/?ref_=adv_li_tt"
  },
  {
    "rank": "39",
    "movieName": "Bodies Bodies Bodies",
    "link": "https://www.imdb.com/title/tt8110652/?ref_=adv_li_tt"
  },
  {
    "rank": "40",
    "movieName": "Purple Hearts",
    "link": "https://www.imdb.com/title/tt4614584/?ref_=adv_li_tt"
  },
  {
    "rank": "41",
    "movieName": "Avatar: The Way of Water",
    "link": "https://www.imdb.com/title/tt1630029/?ref_=adv_li_tt"
  },
  {
    "rank": "42",
    "movieName": "Honk for Jesus. Save Your Soul.",
    "link": "https://www.imdb.com/title/tt12655436/?ref_=adv_li_tt"
  },
  {
    "rank": "43",
    "movieName": "The Next 365 Days",
    "link": "https://www.imdb.com/title/tt21106646/?ref_=adv_li_tt"
  },
  {
    "rank": "44",
    "movieName": "Doctor Strange in the Multiverse of Madness",
    "link": "https://www.imdb.com/title/tt9419884/?ref_=adv_li_tt"
  },
  {
    "rank": "45",
    "movieName": "Lightyear",
    "link": "https://www.imdb.com/title/tt10298810/?ref_=adv_li_tt"
  },
  {
    "rank": "46",
    "movieName": "That's Amor",
    "link": "https://www.imdb.com/title/tt21388556/?ref_=adv_li_tt"
  },
  {
    "rank": "47",
    "movieName": "Death on the Nile",
    "link": "https://www.imdb.com/title/tt7657566/?ref_=adv_li_tt"
  },
  {
    "rank": "48",
    "movieName": "Barbarian",
    "link": "https://www.imdb.com/title/tt15791034/?ref_=adv_li_tt"
  },
  {
    "rank": "49",
    "movieName": "Karthikeya 2",
    "link": "https://www.imdb.com/title/tt13664684/?ref_=adv_li_tt"
  },
  {
    "rank": "50",
    "movieName": "Triangle of Sadness",
    "link": "https://www.imdb.com/title/tt7322224/?ref_=adv_li_tt"
  }
]
