[
  {
    "name": "Project Hail Mary",
    "link": "https://www.imdb.com/title/tt12042730/",
    "rating": "8.4",
    "votes": "229205",
    "year": "2026",
    "releaseDate": "20/3/2026",
    "genres": "Adventure, Comedy, Sci-Fi",
    "runtime": "9360",
    "plot": "A science teacher wakes up alone on a spaceship. As his memory returns, he uncovers a mission to stop a mysterious substance killing Earth's sun and that an unexpected friendship may be the key.",
    "image": "https://m.media-amazon.com/images/M/MV5BNTkwNzJiYTctNzI3NC00NjE1LTlhYjktY2Q5MTdmMWFmNzcxXkEyXkFqcGc@._V1_.jpg",
    "imageCaption": "Ryan Gosling and James Ortiz in Project Hail Mary (2026)",
    "metascore": "77",
    "certificate": "PG-13",
    "status": "Released"
  },
  {
    "name": "Lee Cronin's The Mummy",
    "link": "https://www.imdb.com/title/tt32612507/",
    "rating": "6.4",
    "votes": "8865",
    "year": "2026",
    "releaseDate": "17/4/2026",
    "genres": "Horror",
    "runtime": "8040",
    "plot": "The young daughter of a journalist disappears into the desert without a trace. Eight years later, the broken family is shocked when she is returned to them, as what should be a joyful reunion turns into a living nightmare.",
    "image": "https://m.media-amazon.com/images/M/MV5BNWQ1NzI2YTUtN2E0ZS00YzVmLTkxNjktMWIzNTYwMzkyOTU0XkEyXkFqcGc@._V1_.jpg",
    "imageCaption": "Natalie Grace in Lee Cronin's The Mummy (2026)",
    "metascore": "46",
    "certificate": "R",
    "status": "Released"
  },
  {
    "name": "Street Fighter",
    "link": "https://www.imdb.com/title/tt27419420/",
    "rating": "0",
    "votes": "0",
    "year": "2026",
    "releaseDate": "16/10/2026",
    "genres": "Action, Drama",
    "runtime": "",
    "plot": "Street Fighters Ryu and Ken reunite when Chun-Li recruits them for the World Warrior Tournament. As they face a hidden conspiracy, they must confront each other and their past-or face destruction.",
    "image": "https://m.media-amazon.com/images/M/MV5BYjhlN2EyNGUtY2U4YS00ZTQ3LTg0NTgtNGIxZmVhMDlmMjIyXkEyXkFqcGc@._V1_.jpg",
    "imageCaption": "Callina Liang, Noah Centineo, and Andrew Koji in Street Fighter (2026)",
    "metascore": "",
    "certificate": "",
    "status": "Post-production"
  },
  {
    "name": "Thrash",
    "link": "https://www.imdb.com/title/tt32362890/",
    "rating": "5",
    "votes": "19802",
    "year": "2026",
    "releaseDate": "10/4/2026",
    "genres": "Horror, Thriller",
    "runtime": "5160",
    "plot": "When a Category 5 hurricane decimates a coastal town, the storm surge brings devastation, chaos and something far more frightening: hungry sharks.",
    "image": "https://m.media-amazon.com/images/M/MV5BODMxNjdhMWQtMmJhYS00MDc1LTkyYzAtYTgzZTFhMmI1ODEyXkEyXkFqcGc@._V1_.jpg",
    "imageCaption": "Phoebe Dynevor in Thrash (2026)",
    "metascore": "48",
    "certificate": "R",
    "status": "Released"
  },
  {
    "name": "Roommates",
    "link": "https://www.imdb.com/title/tt37540875/",
    "rating": "5.7",
    "votes": "2700",
    "year": "2026",
    "releaseDate": "17/4/2026",
    "genres": "Comedy",
    "runtime": "6420",
    "plot": "When a hopeful, naive college freshman, Devon, asks the cool and confident Celeste to be her roommate, a blossoming friendship spirals into a war of passive aggression.",
    "image": "https://m.media-amazon.com/images/M/MV5BYjk2YmRhNTItOGY5Ni00MjgwLTk4ZGMtMzE0MTQzMmMxYWRlXkEyXkFqcGc@._V1_.jpg",
    "imageCaption": "Sadie Sandler and Chloe East in Roommates (2026)",
    "metascore": "57",
    "certificate": "R",
    "status": "Released"
  },
  {
    "name": "The Super Mario Galaxy Movie",
    "link": "https://www.imdb.com/title/tt28650488/",
    "rating": "6.4",
    "votes": "38187",
    "year": "2026",
    "releaseDate": "1/4/2026",
    "genres": "Animation, Adventure, Comedy",
    "runtime": "5880",
    "plot": "Mario ventures into space, exploring cosmic worlds and tackling galactic challenges far from the familiar Mushroom Kingdom.",
    "image": "https://m.media-amazon.com/images/M/MV5BMDg5MjRkNWEtYmU1Mi00MTExLTk5MDQtY2RiMWVkZWNiOThjXkEyXkFqcGc@._V1_.jpg",
    "imageCaption": "Jack Black, Charlie Day, Luis Guzmán, Brie Larson, Chris Pratt, Keegan-Michael Key, Benny Safdie, Virginia Dare Jelenic, Donald Glover, and Anya Taylor-Joy in The Super Mario Galaxy Movie (2026)",
    "metascore": "37",
    "certificate": "PG",
    "status": "Released"
  },
  {
    "name": "The Drama",
    "link": "https://www.imdb.com/title/tt33071426/",
    "rating": "7.5",
    "votes": "33364",
    "year": "2026",
    "releaseDate": "3/4/2026",
    "genres": "Comedy, Drama, Romance",
    "runtime": "6300",
    "plot": "A happily-engaged couple is put to the test when an unexpected turn sends their wedding week off the rails.",
    "image": "https://m.media-amazon.com/images/M/MV5BMTcwOGZhYmItYTg3ZS00NjUwLWJiMmQtMjU5YjEwYWY0NmNkXkEyXkFqcGc@._V1_.jpg",
    "imageCaption": "Robert Pattinson and Zendaya in The Drama (2026)",
    "metascore": "59",
    "certificate": "R",
    "status": "Released"
  },
  {
    "name": "Balls Up",
    "link": "https://www.imdb.com/title/tt26735622/",
    "rating": "4.6",
    "votes": "4913",
    "year": "2026",
    "releaseDate": "15/4/2026",
    "genres": "Action, Comedy, Crime",
    "runtime": "6240",
    "plot": "Two marketers pitch a bold new condom World Cup sponsorship. After a booze-fueled scandal, they must outrun chaos to survive.",
    "image": "https://m.media-amazon.com/images/M/MV5BZjJlMDFmOWMtY2NhZS00MzAwLWFiOWQtNzBiZDNiOWRiMDA4XkEyXkFqcGc@._V1_.jpg",
    "imageCaption": "Mark Wahlberg and Paul Walter Hauser in Balls Up (2026)",
    "metascore": "34",
    "certificate": "R",
    "status": "Released"
  },
  {
    "name": "Crime 101",
    "link": "https://www.imdb.com/title/tt32430579/",
    "rating": "6.8",
    "votes": "60925",
    "year": "2026",
    "releaseDate": "13/2/2026",
    "genres": "Crime, Drama, Thriller",
    "runtime": "8400",
    "plot": "An elusive thief, eyeing his final score, encounters a disillusioned insurance broker at her own crossroads. As their paths intertwine, a relentless detective trails them hoping to thwart the multi-million dollar heist they are planning.",
    "image": "https://m.media-amazon.com/images/M/MV5BZThlN2M4ZTUtYTU3Mi00MDE5LWFhYWUtNjkxMWEwNjUwNDVhXkEyXkFqcGc@._V1_.jpg",
    "imageCaption": "Halle Berry, Mark Ruffalo, Chris Hemsworth, and Barry Keoghan in Crime 101 (2026)",
    "metascore": "68",
    "certificate": "R",
    "status": "Released"
  },
  {
    "name": "Michael",
    "link": "https://www.imdb.com/title/tt11378946/",
    "rating": "0",
    "votes": "0",
    "year": "2026",
    "releaseDate": "24/4/2026",
    "genres": "Biography, Drama, History",
    "runtime": "7620",
    "plot": "The story of the famous musician Michael Jackson, known as the King of Pop.",
    "image": "https://m.media-amazon.com/images/M/MV5BNzllNmRlN2EtMDQyOC00ODJjLTg4OWQtZDNmNGU3YzlkNjc1XkEyXkFqcGc@._V1_.jpg",
    "imageCaption": "Jaafar Jackson in Michael (2026)",
    "metascore": "38",
    "certificate": "PG-13",
    "status": "Released"
  },
  {
    "name": "Outcome",
    "link": "https://www.imdb.com/title/tt23724682/",
    "rating": "4.5",
    "votes": "6283",
    "year": "2026",
    "releaseDate": "10/4/2026",
    "genres": "Comedy, Crime, Drama",
    "runtime": "4980",
    "plot": "Hollywood star Reef he is forced to confront his problems and atone for his past after being threatened by a bizarre video footage from his past.",
    "image": "https://m.media-amazon.com/images/M/MV5BMzFmMWExMmMtZmYwZi00ZDIyLTlhYTUtZmM3ZTBlZWNjOWY4XkEyXkFqcGc@._V1_.jpg",
    "imageCaption": "Keanu Reeves in Outcome (2026)",
    "metascore": "37",
    "certificate": "R",
    "status": "Released"
  },
  {
    "name": "Ready or Not 2: Here I Come",
    "link": "https://www.imdb.com/title/tt33978029/",
    "rating": "6.7",
    "votes": "21529",
    "year": "2026",
    "releaseDate": "20/3/2026",
    "genres": "Comedy, Horror, Thriller",
    "runtime": "6480",
    "plot": "After surviving one deadly game, Grace and her sister Faith must now outrun four rival families competing for a powerful throne - winner takes all.",
    "image": "https://m.media-amazon.com/images/M/MV5BZTM3N2EyMTEtNDhkMi00ZjNiLWI0MWUtOGViMjExODY3YTJhXkEyXkFqcGc@._V1_.jpg",
    "imageCaption": "David Cronenberg, Elijah Wood, Sarah Michelle Gellar, Nestor Carbonell, Shawn Hatosy, Kevin Durand, Kathryn Newton, Dan Beirne, Maia Jae, Juan Pablo Romero, Olivia Cheng, Samara Weaving, Varun Saranga, Nadeem Umar-Khitab, Masa Lizdek, and Antony Hall in Ready or Not 2: Here I Come (2026)",
    "metascore": "58",
    "certificate": "R",
    "status": "Released"
  },
  {
    "name": "Dhurandhar The Revenge",
    "link": "https://www.imdb.com/title/tt39139925/",
    "rating": "8.5",
    "votes": "47047",
    "year": "2026",
    "releaseDate": "19/3/2026",
    "genres": "Action, Crime, Thriller",
    "runtime": "13800",
    "plot": "Jaskirat Singh Rangi descends deeper into his alias as Hamza Ali Mazari, rising through Karachi's criminal hierarchy to claim the feared title \"Sher-e-Baloch\" while balancing loyalty, betrayal, and survival in a ruthless underworld.",
    "image": "https://m.media-amazon.com/images/M/MV5BNzdkNjAxNWMtNWY3My00NTI1LTg2YWQtOGI3MDA0NzdhMjEyXkEyXkFqcGc@._V1_.jpg",
    "imageCaption": "Dhurandhar The Revenge (2026)",
    "metascore": "",
    "certificate": "",
    "status": "Released"
  },
  {
    "name": "Send Help",
    "link": "https://www.imdb.com/title/tt8036976/",
    "rating": "6.8",
    "votes": "74928",
    "year": "2026",
    "releaseDate": "30/1/2026",
    "genres": "Adventure, Horror, Thriller",
    "runtime": "6780",
    "plot": "When an employee and her insufferable boss become stranded on a deserted island, the only survivors of a plane crash, they must overcome past grievances and work together to make it out alive.",
    "image": "https://m.media-amazon.com/images/M/MV5BOTgxOWY5NTMtYjdiNi00NTIyLTkwMTQtMWNjM2IzYTU0ODgyXkEyXkFqcGc@._V1_.jpg",
    "imageCaption": "Rachel McAdams and Dylan O'Brien in Send Help (2026)",
    "metascore": "75",
    "certificate": "R",
    "status": "Released"
  },
  {
    "name": "180",
    "link": "https://www.imdb.com/title/tt40891145/",
    "rating": "4.6",
    "votes": "710",
    "year": "2026",
    "releaseDate": "17/4/2026",
    "genres": "Crime, Drama, Thriller",
    "runtime": "5640",
    "plot": "When an unexpected road rage incident puts his son in critical condition, an enraged father spirals down a dark path of emotional turmoil and vengeance.",
    "image": "https://m.media-amazon.com/images/M/MV5BN2NhYzE1YTUtNDA0Yi00ZjhlLWEyMzUtN2UxMzkzZTdkMDRlXkEyXkFqcGc@._V1_.jpg",
    "imageCaption": "180 (2026)",
    "metascore": "",
    "certificate": "TV-MA",
    "status": "Released"
  },
  {
    "name": "Focker-in-Law",
    "link": "https://www.imdb.com/title/tt34966140/",
    "rating": "0",
    "votes": "0",
    "year": "2026",
    "releaseDate": "25/11/2026",
    "genres": "Comedy",
    "runtime": "",
    "plot": "A young man named Henry, son of Greg and Pam Focker, faces family chaos when he decides to marry a strong-willed woman who appears to be his complete mismatch.",
    "image": "https://m.media-amazon.com/images/M/MV5BOGI0NjhmMmEtNDAxZC00MDFjLThlNzUtYTUwMDkzMjMxNGIzXkEyXkFqcGc@._V1_.jpg",
    "imageCaption": "Robert De Niro, Ben Stiller, and Ariana Grande in Focker-in-Law (2026)",
    "metascore": "",
    "certificate": "",
    "status": "Post-production"
  },
  {
    "name": "The Legend of Aang: The Last Airbender",
    "link": "https://www.imdb.com/title/tt18259538/",
    "rating": "0",
    "votes": "0",
    "year": "2026",
    "releaseDate": "9/10/2026",
    "genres": "Animation, Action, Adventure",
    "runtime": "5940",
    "plot": "Avatar Aang, the world's last Airbender, learns of an ancient power that could save his culture from extinction. With the help of his friends, he embarks on a global quest to find it before it falls into the wrong hands.",
    "image": "https://m.media-amazon.com/images/M/MV5BYjI3Y2Q0ZjgtNWM3Ny00OWQ2LWE2MjMtN2VhMjQ2MzljYzdkXkEyXkFqcGc@._V1_.jpg",
    "imageCaption": "Dionne Quan, Dave Bautista, Steven Yeun, Jessica Matten, Román Zaragoza, and Eric Nam in The Legend of Aang: The Last Airbender (2026)",
    "metascore": "",
    "certificate": "",
    "status": "Completed"
  },
  {
    "name": "Tom Clancy's Jack Ryan: Ghost War",
    "link": "https://www.imdb.com/title/tt34378301/",
    "rating": "0",
    "votes": "0",
    "year": "2026",
    "releaseDate": "20/5/2026",
    "genres": "Action, Drama, Thriller",
    "runtime": "6300",
    "plot": "Follows Jack Ryan who reunites with CIA operatives to navigate a treacherous web of betrayal against an enemy who knows their every move, facing a past they thought was long put to rest.",
    "image": "https://m.media-amazon.com/images/M/MV5BZGVkZjAxMzYtNGE5YS00ZWEwLTk0NGMtY2Q4MWJiN2YyZDA2XkEyXkFqcGc@._V1_.jpg",
    "imageCaption": "John Krasinski in Tom Clancy's Jack Ryan: Ghost War (2026)",
    "metascore": "",
    "certificate": "R",
    "status": "Completed"
  },
  {
    "name": "Toaster",
    "link": "https://www.imdb.com/title/tt34498610/",
    "rating": "4.7",
    "votes": "2103",
    "year": "2026",
    "releaseDate": "15/4/2026",
    "genres": "Comedy, Drama, Thriller",
    "runtime": "7200",
    "plot": "Murder and chaos erupt when a miser becomes obsessed with a toaster he gave as a wedding gift.",
    "image": "https://m.media-amazon.com/images/M/MV5BZDk0YzdmOTAtNTFmMi00NTQ0LThhMTAtNGY1NDRkNmIyODdmXkEyXkFqcGc@._V1_.jpg",
    "imageCaption": "Rajkummar Rao in Toaster (2026)",
    "metascore": "",
    "certificate": "TV-14",
    "status": "Released"
  },
  {
    "name": "The Hunger Games: Sunrise on the Reaping",
    "link": "https://www.imdb.com/title/tt32558705/",
    "rating": "0",
    "votes": "0",
    "year": "2026",
    "releaseDate": "20/11/2026",
    "genres": "Action, Adventure, Drama",
    "runtime": "9000",
    "plot": "Revisit he world of Panem 24 years before the events of The Hunger Games, starting on the morning of the reaping of the 50th Hunger Games, also known as the Second Quarter Quell.",
    "image": "https://m.media-amazon.com/images/M/MV5BNGRkYmM2MjUtZTY4Yi00YTNhLTk1MDEtYTQ3YjFiOTljM2Y1XkEyXkFqcGc@._V1_.jpg",
    "imageCaption": "Joseph Zada, Laura Marcus, and Jhaleil Swaby in The Hunger Games: Sunrise on the Reaping (2026)",
    "metascore": "",
    "certificate": "",
    "status": "Post-production"
  },
  {
    "name": "Avengers: Doomsday",
    "link": "https://www.imdb.com/title/tt21357150/",
    "rating": "0",
    "votes": "0",
    "year": "2026",
    "releaseDate": "18/12/2026",
    "genres": "Action, Adventure, Sci-Fi",
    "runtime": "",
    "plot": "Plot under wraps.",
    "image": "https://m.media-amazon.com/images/M/MV5BM2E1ZTJiZTgtZGI2Zi00MzAxLThhZjktMmU3M2E3Yzk3NjUxXkEyXkFqcGc@._V1_.jpg",
    "imageCaption": "Greg D'Agostino in Avengers: Doomsday (2026)",
    "metascore": "",
    "certificate": "",
    "status": "Post-production"
  },
  {
    "name": "Reminders of Him",
    "link": "https://www.imdb.com/title/tt33714084/",
    "rating": "6.3",
    "votes": "6240",
    "year": "2026",
    "releaseDate": "13/3/2026",
    "genres": "Drama, Romance",
    "runtime": "6840",
    "plot": "After prison, a woman attempts to reconnect with her young daughter but faces resistance from everyone except a bar owner with ties to her child. As they grow closer, she must confront her past mistakes to build a hopeful future.",
    "image": "https://m.media-amazon.com/images/M/MV5BNjI4OGM1NDEtYzA1NS00ZDg3LWFmZjUtMjg1MGQ4MTk3NjQzXkEyXkFqcGc@._V1_.jpg",
    "imageCaption": "Maika Monroe in Reminders of Him (2026)",
    "metascore": "49",
    "certificate": "PG-13",
    "status": "Released"
  },
  {
    "name": "War Machine",
    "link": "https://www.imdb.com/title/tt15940132/",
    "rating": "6.3",
    "votes": "88962",
    "year": "2026",
    "releaseDate": "6/3/2026",
    "genres": "Action, Sci-Fi, Thriller",
    "runtime": "6360",
    "plot": "Follow the final recruits of a grueling special ops boot camp who encounter a mysterious deadly force.",
    "image": "https://m.media-amazon.com/images/M/MV5BMmM1ZTc5ZTYtOTM2My00MjBmLWE5NzktYzkyYzdlYWE3ZDAzXkEyXkFqcGc@._V1_.jpg",
    "imageCaption": "Alan Ritchson in War Machine (2026)",
    "metascore": "54",
    "certificate": "R",
    "status": "Released"
  },
  {
    "name": "Busboys",
    "link": "https://www.imdb.com/title/tt34705112/",
    "rating": "5.2",
    "votes": "424",
    "year": "2026",
    "releaseDate": "17/4/2026",
    "genres": "Comedy",
    "runtime": "5820",
    "plot": "A pair of idiot friends believe that if they become waiters, all of their problems will be solved. They aren't entirely wrong, but they aren't entirely right.",
    "image": "https://m.media-amazon.com/images/M/MV5BZTNiNzA4YWYtMjgxMy00NzJhLWJkMjQtMGMxZjA4N2VlNGU3XkEyXkFqcGc@._V1_.jpg",
    "imageCaption": "David Spade and Theo Von in Busboys (2026)",
    "metascore": "",
    "certificate": "R",
    "status": "Released"
  },
  {
    "name": "Bhooth Bangla",
    "link": "https://www.imdb.com/title/tt29540862/",
    "rating": "7.4",
    "votes": "11169",
    "year": "2026",
    "releaseDate": "16/4/2026",
    "genres": "Comedy, Horror",
    "runtime": "10380",
    "plot": "A man inherits a palace in rural Mangalpur and plans his sister's wedding there, but strange supernatural events and panicked locals force him to investigate the property's mysterious past.",
    "image": "https://m.media-amazon.com/images/M/MV5BN2Y3NjRhYmMtNWVjMy00ZmE1LWJkNGYtNDY3Y2I3NjkzOGE0XkEyXkFqcGc@._V1_.jpg",
    "imageCaption": "Akshay Kumar in Bhooth Bangla (2026)",
    "metascore": "",
    "certificate": "",
    "status": "Released"
  },
  {
    "name": "Mercy",
    "link": "https://www.imdb.com/title/tt31050594/",
    "rating": "6.2",
    "votes": "58232",
    "year": "2026",
    "releaseDate": "23/1/2026",
    "genres": "Action, Crime, Drama",
    "runtime": "5940",
    "plot": "Set in the near future, a detective accused of murdering his wife has 90 minutes to prove his innocence to an advanced AI judge.",
    "image": "https://m.media-amazon.com/images/M/MV5BMWJmYjcwMTMtMDU1ZC00ZGI5LTlmZDAtODI3NDA2ZTE5ZGVlXkEyXkFqcGc@._V1_.jpg",
    "imageCaption": "Rebecca Ferguson and Chris Pratt in Mercy (2026)",
    "metascore": "34",
    "certificate": "PG-13",
    "status": "Released"
  },
  {
    "name": "Hoppers",
    "link": "https://www.imdb.com/title/tt26443616/",
    "rating": "7.4",
    "votes": "35253",
    "year": "2026",
    "releaseDate": "6/3/2026",
    "genres": "Animation, Adventure, Comedy",
    "runtime": "6240",
    "plot": "A 19-year-old animal lover uses technology that places her consciousness into a robotic beaver to uncover mysteries within the animal world beyond her imagination.",
    "image": "https://m.media-amazon.com/images/M/MV5BNzRiMzZlMTMtNmU3OC00MDUwLThmNDUtMTBjZmQ3MWQ4NTljXkEyXkFqcGc@._V1_.jpg",
    "imageCaption": "Melissa Villaseñor and Piper Curda in Hoppers (2026)",
    "metascore": "73",
    "certificate": "PG",
    "status": "Released"
  },
  {
    "name": "Mike & Nick & Nick & Alice",
    "link": "https://www.imdb.com/title/tt27552099/",
    "rating": "6.2",
    "votes": "15567",
    "year": "2026",
    "releaseDate": "27/3/2026",
    "genres": "Action, Comedy, Crime",
    "runtime": "6420",
    "plot": "Two friends navigate the dangerous world of organized crime, testing their loyalty and survival skills as they get deeper into the criminal underworld.",
    "image": "https://m.media-amazon.com/images/M/MV5BZDBiNjIyNjUtNWZlYy00MGU4LWFjNDUtMGExYTZlNmNhZTY4XkEyXkFqcGc@._V1_.jpg",
    "imageCaption": "Vince Vaughn, James Marsden, and Eiza González in Mike & Nick & Nick & Alice (2026)",
    "metascore": "70",
    "certificate": "R",
    "status": "Released"
  },
  {
    "name": "Wuthering Heights",
    "link": "https://www.imdb.com/title/tt32897959/",
    "rating": "6.1",
    "votes": "58394",
    "year": "2026",
    "releaseDate": "13/2/2026",
    "genres": "Drama, Romance",
    "runtime": "8160",
    "plot": "A passionate and tumultuous love story set against the backdrop of the Yorkshire moors, exploring the intense and destructive relationship between Heathcliff and Catherine Earnshaw.",
    "image": "https://m.media-amazon.com/images/M/MV5BMGFlMTVkMDktZGMzMC00Yjk4LWFmNzEtNTFmMzM2YzM3MWFkXkEyXkFqcGc@._V1_.jpg",
    "imageCaption": "Margot Robbie and Jacob Elordi in Wuthering Heights (2026)",
    "metascore": "55",
    "certificate": "R",
    "status": "Released"
  },
  {
    "name": "28 Years Later: The Bone Temple",
    "link": "https://www.imdb.com/title/tt32141377/",
    "rating": "7.3",
    "votes": "86483",
    "year": "2026",
    "releaseDate": "16/1/2026",
    "genres": "Horror, Sci-Fi, Thriller",
    "runtime": "6540",
    "plot": "As Spike is inducted into Jimmy Crystal's gang on the mainland, Dr. Kelson makes a discovery that could alter the world.",
    "image": "https://m.media-amazon.com/images/M/MV5BZGU2M2Y1YTItMWYxNS00NDYxLThhOTYtNjNhOWUzNjA3MTYwXkEyXkFqcGc@._V1_.jpg",
    "imageCaption": "Ralph Fiennes, Alfie Williams, Jack O'Connell, Chi Lewis-Parry, and Erin Kellyman in 28 Years Later: The Bone Temple (2026)",
    "metascore": "81",
    "certificate": "R",
    "status": "Released"
  },
  {
    "name": "Peaky Blinders: The Immortal Man",
    "link": "https://www.imdb.com/title/tt15574124/",
    "rating": "6.5",
    "votes": "69835",
    "year": "2026",
    "releaseDate": "20/3/2026",
    "genres": "Crime, Drama, History",
    "runtime": "6720",
    "plot": "During World War II, Tommy Shelby returns to a bombed Birmingham and becomes involved in secret wartime missions facing new threats as he reckons with his past.",
    "image": "https://m.media-amazon.com/images/M/MV5BNTdlNTNjNjctYTg2MC00NTFlLTliNTctODFiZjZmNWRkYTVlXkEyXkFqcGc@._V1_.jpg",
    "imageCaption": "Cillian Murphy in Peaky Blinders: The Immortal Man (2026)",
    "metascore": "59",
    "certificate": "R",
    "status": "Released"
  },
  {
    "name": "Mother Mary",
    "link": "https://www.imdb.com/title/tt27200708/",
    "rating": "0",
    "votes": "0",
    "year": "2026",
    "releaseDate": "21/5/2026",
    "genres": "Drama, Music, Thriller",
    "runtime": "6720",
    "plot": "Long-buried wounds rise to the surface when iconic pop star Mother Mary reunites with her estranged best friend and former costume designer, Sam Anselm, on the eve of her comeback performance.",
    "image": "https://m.media-amazon.com/images/M/MV5BZWM0NTIzMWEtOWU1ZC00OTEyLThmNTItYjM1N2Y1MDllMGYzXkEyXkFqcGc@._V1_.jpg",
    "imageCaption": "Anne Hathaway in Mother Mary (2026)",
    "metascore": "56",
    "certificate": "R",
    "status": "Released"
  },
  {
    "name": "The Dog Stars",
    "link": "https://www.imdb.com/title/tt21285562/",
    "rating": "0",
    "votes": "0",
    "year": "2026",
    "releaseDate": "28/8/2026",
    "genres": "Action, Adventure, Sci-Fi",
    "runtime": "",
    "plot": "In a post-apocalyptic world, a virus wipes out humanity. Survivors face roaming scavengers called Reapers. Protagonist Hig, a pilot, survived the flu but lost his wife.",
    "image": "https://m.media-amazon.com/images/M/MV5BMDBkZTNhMmQtMjliNS00OTIyLWI1OTItYzEzZTU0NGU0NTI4XkEyXkFqcGc@._V1_.jpg",
    "imageCaption": "Josh Brolin and Jacob Elordi in The Dog Stars (2026)",
    "metascore": "",
    "certificate": "",
    "status": "Post-production"
  },
  {
    "name": "The Odyssey",
    "link": "https://www.imdb.com/title/tt33764258/",
    "rating": "0",
    "votes": "0",
    "year": "2026",
    "releaseDate": "17/7/2026",
    "genres": "Action, Adventure, Fantasy",
    "runtime": "",
    "plot": "After the Trojan War, Odysseus faces a dangerous voyage back to Ithaca, meeting creatures like the Cyclops Polyphemus, Sirens, and Circe along the way.",
    "image": "https://m.media-amazon.com/images/M/MV5BN2MyYjk2MWMtODMyZS00MDUyLWE0OGQtOTQ3MGY0MDE0ZjVmXkEyXkFqcGc@._V1_.jpg",
    "imageCaption": "The Odyssey (2026)",
    "metascore": "",
    "certificate": "",
    "status": "Completed"
  },
  {
    "name": "Tu Yaa Main",
    "link": "https://www.imdb.com/title/tt36118360/",
    "rating": "6.7",
    "votes": "5407",
    "year": "2026",
    "releaseDate": "13/2/2026",
    "genres": "Romance, Thriller",
    "runtime": "8580",
    "plot": "Two content creators' adventure becomes a deadly game of survival, forcing them to navigate both nature's dangers and their own rivalry.",
    "image": "https://m.media-amazon.com/images/M/MV5BOGIzNWVkODctYWNmZS00MGU2LWI3ZGItY2Q0YTAyYzEzMDA5XkEyXkFqcGc@._V1_.jpg",
    "imageCaption": "Shanaya Kapoor and Adarsh Gourav in Tu Yaa Main (2026)",
    "metascore": "",
    "certificate": "",
    "status": "Released"
  },
  {
    "name": "Passenger",
    "link": "https://www.imdb.com/title/tt33763941/",
    "rating": "0",
    "votes": "0",
    "year": "2026",
    "releaseDate": "22/5/2026",
    "genres": "Horror",
    "runtime": "5640",
    "plot": "After a young couple witnesses a gruesome highway accident, they soon realize they did not leave the crash scene alone, as a demonic presence called the Passenger won't stop until it claims them both.",
    "image": "https://m.media-amazon.com/images/M/MV5BMThhNTE5NGQtMWFmNC00ODlmLTk1YTUtNzVmMGVhZjliNDU2XkEyXkFqcGc@._V1_.jpg",
    "imageCaption": "Passenger (2026)",
    "metascore": "",
    "certificate": "",
    "status": "Completed"
  },
  {
    "name": "Mortal Kombat II",
    "link": "https://www.imdb.com/title/tt17490712/",
    "rating": "0",
    "votes": "0",
    "year": "2026",
    "releaseDate": "8/5/2026",
    "genres": "Action, Adventure, Fantasy",
    "runtime": "6960",
    "plot": "The fan favorite champions -- now joined by Johnny Cage himself -- are pitted against one another in the ultimate battle to defeat the dark rule of Shao Kahn that threatens the very existence of the Earthrealm and its defenders.",
    "image": "https://m.media-amazon.com/images/M/MV5BNTg2YWNkN2EtMzc1Ny00ZTBhLWFmYTItMmMyNzhjNjhhNmVhXkEyXkFqcGc@._V1_.jpg",
    "imageCaption": "Tadanobu Asano, Damon Herriman, Josh Lawson, Hiroyuki Sanada, Karl Urban, Ana Thu Nguyen, CJ Bloomfield, Lewis Tan, Mehcad Brooks, Chin Han, Jessica McNamee, Joe Taslim, Ludi Lin, Desmond Chiam, Max Huang, Tati Gabrielle, Martyn Ford, and Adeline Rudolph in Mortal Kombat II (2026)",
    "metascore": "",
    "certificate": "R",
    "status": "Completed"
  },
  {
    "name": "The Devil Wears Prada 2",
    "link": "https://www.imdb.com/title/tt33612209/",
    "rating": "0",
    "votes": "0",
    "year": "2026",
    "releaseDate": "1/5/2026",
    "genres": "Comedy, Drama",
    "runtime": "7140",
    "plot": "As Miranda Priestly nears retirement, she reunites with Andy Sachs to face off against her former assistant turned rival: Emily Charlton.",
    "image": "https://m.media-amazon.com/images/M/MV5BZmM3ZDU3ODItZmY5Yi00OTQ2LWE5OTctZTA5NDBhMWJkOGY3XkEyXkFqcGc@._V1_.jpg",
    "imageCaption": "Meryl Streep, Stanley Tucci, Anne Hathaway, and Emily Blunt in The Devil Wears Prada 2 (2026)",
    "metascore": "",
    "certificate": "PG-13",
    "status": "Completed"
  },
  {
    "name": "GOAT",
    "link": "https://www.imdb.com/title/tt27613895/",
    "rating": "6.7",
    "votes": "15788",
    "year": "2026",
    "releaseDate": "13/2/2026",
    "genres": "Animation, Action, Adventure",
    "runtime": "6000",
    "plot": "A small goat with big dreams gets a once-in-a-lifetime shot to join the pros and play roarball, a high-intensity, co-ed, full-contact sport dominated by the fastest, fiercest animals in the world.",
    "image": "https://m.media-amazon.com/images/M/MV5BYzE5OTJkOGMtYWFiNi00NTlkLWE3ZWItY2ZlNjkyOWVhMjMyXkEyXkFqcGc@._V1_.jpg",
    "imageCaption": "Wayne Knight, Gabrielle Union, David Harbour, Rayaan Kamal Khan, Savannah Van Van McConneaughey, Nick Kroll, Angelo Kouyate, Cassius Peyton, Kingston Peyton, Nicola Coughlan, Stephen Curry, Caleb McLaughlin, and Aaron Pierre in GOAT (2026)",
    "metascore": "60",
    "certificate": "PG",
    "status": "Released"
  },
  {
    "name": "Star Wars: The Mandalorian and Grogu",
    "link": "https://www.imdb.com/title/tt30825738/",
    "rating": "0",
    "votes": "0",
    "year": "2026",
    "releaseDate": "22/5/2026",
    "genres": "Action, Adventure, Family",
    "runtime": "7920",
    "plot": "Once a lone bounty hunter, Mandalorian Din Djarin and his apprentice Grogu embark on an exciting new Star Wars adventure.",
    "image": "https://m.media-amazon.com/images/M/MV5BYzVkMmJhNTgtNjYwOS00YjM0LThlNWEtNGExNmIxZjVkMmJhXkEyXkFqcGc@._V1_.jpg",
    "imageCaption": "Pedro Pascal and Grogu in Star Wars: The Mandalorian and Grogu (2026)",
    "metascore": "",
    "certificate": "PG-13",
    "status": "Post-production"
  },
  {
    "name": "Shelter",
    "link": "https://www.imdb.com/title/tt32357218/",
    "rating": "6.1",
    "votes": "25991",
    "year": "2026",
    "releaseDate": "30/1/2026",
    "genres": "Action, Thriller",
    "runtime": "6420",
    "plot": "Michael Mason is a recluse on a remote Scottish island who rescues a girl from the sea, unleashing a perilous sequence of events that culminate in an attack on his home, compelling him to face his turbulent history.",
    "image": "https://m.media-amazon.com/images/M/MV5BMzI2ODY3MzQtYzllNy00YWM1LWExZTgtOGIwNjk2MmE2MmY2XkEyXkFqcGc@._V1_.jpg",
    "imageCaption": "Jason Statham and Bodhi Rae Breathnach in Shelter (2026)",
    "metascore": "50",
    "certificate": "R",
    "status": "Released"
  },
  {
    "name": "How to Make a Killing",
    "link": "https://www.imdb.com/title/tt4357198/",
    "rating": "6.5",
    "votes": "19235",
    "year": "2026",
    "releaseDate": "20/2/2026",
    "genres": "Comedy, Drama, Thriller",
    "runtime": "6300",
    "plot": "Disowned at birth by his obscenely wealthy family, a blue-collar will stop at nothing to reclaim his inheritance, no matter how many relatives stand in his way.",
    "image": "https://m.media-amazon.com/images/M/MV5BOTkwY2JjMWYtOGU4YS00ZTg0LWIzYzUtZDkxNDE5NWNkNWM1XkEyXkFqcGc@._V1_.jpg",
    "imageCaption": "Glen Powell in How to Make a Killing (2026)",
    "metascore": "49",
    "certificate": "R",
    "status": "Released"
  },
  {
    "name": "You, Me & Tuscany",
    "link": "https://www.imdb.com/title/tt36352591/",
    "rating": "6.4",
    "votes": "1893",
    "year": "2026",
    "releaseDate": "10/4/2026",
    "genres": "Comedy, Romance",
    "runtime": "6300",
    "plot": "When a woman crashes at an empty Italian villa, posing as the owner's fiancée, she discovers an unexpected romance that could transform her life.",
    "image": "https://m.media-amazon.com/images/M/MV5BZjg0MjliNDctMDE3NS00ZmMzLWE1ODUtZDcyN2I3NDE2YmUxXkEyXkFqcGc@._V1_.jpg",
    "imageCaption": "Halle Bailey and Regé-Jean Page in You, Me & Tuscany (2026)",
    "metascore": "53",
    "certificate": "PG-13",
    "status": "Released"
  },
  {
    "name": "Spider-Man: Brand New Day",
    "link": "https://www.imdb.com/title/tt22084616/",
    "rating": "0",
    "votes": "0",
    "year": "2026",
    "releaseDate": "31/7/2026",
    "genres": "Action, Adventure, Fantasy",
    "runtime": "",
    "plot": "A forgotten Peter Parker lives alone as a full-time Spider-Man until mounting pressure triggers a dangerous change and a powerful new enemy emerges.",
    "image": "https://m.media-amazon.com/images/M/MV5BOWNjYWM3NWItOGE0ZS00MWRjLThiZWEtYjc4ZmNmMmU5ZTVmXkEyXkFqcGc@._V1_.jpg",
    "imageCaption": "Zendaya and Tom Holland in Spider-Man: Brand New Day (2026)",
    "metascore": "",
    "certificate": "",
    "status": "Completed"
  },
  {
    "name": "The Bride!",
    "link": "https://www.imdb.com/title/tt30851137/",
    "rating": "5.7",
    "votes": "20944",
    "year": "2026",
    "releaseDate": "6/3/2026",
    "genres": "Drama, Horror, Romance",
    "runtime": "7560",
    "plot": "In 1930s Chicago, Frankenstein asks Dr. Euphronius to help create a companion. They give life to a murdered woman as the Bride, sparking romance, police interest, and radical social change.",
    "image": "https://m.media-amazon.com/images/M/MV5BM2VmMDVlNzgtNThhZC00ZGMwLTg4MmEtZTUzNmRiYTkxYzUyXkEyXkFqcGc@._V1_.jpg",
    "imageCaption": "Christian Bale and Jessie Buckley in The Bride! (2026)",
    "metascore": "55",
    "certificate": "R",
    "status": "Released"
  },
  {
    "name": "Pizza Movie",
    "link": "https://www.imdb.com/title/tt37209937/",
    "rating": "5.8",
    "votes": "6524",
    "year": "2026",
    "releaseDate": "3/4/2026",
    "genres": "Comedy",
    "runtime": "5820",
    "plot": "High college students face an unexpectedly epic journey when they must navigate two flights of stairs to retrieve their pizza delivery, turning a simple task into a surreal adventure.",
    "image": "https://m.media-amazon.com/images/M/MV5BODQxYzE1NDQtOGQ2Zi00YWQ2LTgwMTktODM5YTk4ODI5MTYzXkEyXkFqcGc@._V1_.jpg",
    "imageCaption": "Jack Martin, Caleb Hearon, Marcus Scribner, Sean Giambrone, Lulu Wilson, Gaten Matarazzo, Peyton Elizabeth Lee, and Sarah Sherman in Pizza Movie (2026)",
    "metascore": "64",
    "certificate": "TV-MA",
    "status": "Released"
  },
  {
    "name": "Scream 7",
    "link": "https://www.imdb.com/title/tt27047903/",
    "rating": "5.5",
    "votes": "47465",
    "year": "2026",
    "releaseDate": "27/2/2026",
    "genres": "Horror, Mystery",
    "runtime": "6840",
    "plot": "When a new Ghostface killer emerges in the town where Sidney Prescott has built a new life, her darkest fears are realized as her daughter becomes the next target.",
    "image": "https://m.media-amazon.com/images/M/MV5BMzk2YzRjYmItNTA5Mi00ODczLTljYzUtOWE1ZDFkODhlZWJlXkEyXkFqcGc@._V1_.jpg",
    "imageCaption": "Neve Campbell, Courteney Cox, Mark Consuelos, Ethan Embry, Joel McHale, Asa Germann, Sam Rechner, Anna Camp, Mason Gooding, Timothy Simons, Mckenna Grace, Jasmin Savoy Brown, Isabel May, and Celeste O'Connor in Scream 7 (2026)",
    "metascore": "35",
    "certificate": "R",
    "status": "Released"
  },
  {
    "name": "Faces of Death",
    "link": "https://www.imdb.com/title/tt14619456/",
    "rating": "6.4",
    "votes": "1346",
    "year": "2026",
    "releaseDate": "10/4/2026",
    "genres": "Horror",
    "runtime": "5820",
    "plot": "A woman, employed as a website content moderator, comes across a series of violent videos reproducing death scenes from a film.",
    "image": "https://m.media-amazon.com/images/M/MV5BMGJlZjY2ZGMtYjY0Ny00MTFmLTg0YTItM2MzYTQ4ZGNjMzkxXkEyXkFqcGc@._V1_.jpg",
    "imageCaption": "Dacre Montgomery and Barbie Ferreira in Faces of Death (2026)",
    "metascore": "63",
    "certificate": "R",
    "status": "Released"
  },
  {
    "name": "Hokum",
    "link": "https://www.imdb.com/title/tt35672862/",
    "rating": "7.7",
    "votes": "454",
    "year": "2026",
    "releaseDate": "1/5/2026",
    "genres": "Horror",
    "runtime": "6420",
    "plot": "A horror writer visits an Irish inn to scatter his parents' ashes, unaware the property is said to be haunted by a witch.",
    "image": "https://m.media-amazon.com/images/M/MV5BZjA1ZjFlZGItNTVjZC00NTFhLTg2YTEtODMzODRmNGFiNTdmXkEyXkFqcGc@._V1_.jpg",
    "imageCaption": "Adam Scott in Hokum (2026)",
    "metascore": "79",
    "certificate": "R",
    "status": "Released"
  },
  {
    "name": "Brothers Under Fire",
    "link": "https://www.imdb.com/title/tt32394984/",
    "rating": "4.9",
    "votes": "362",
    "year": "2026",
    "releaseDate": "13/3/2026",
    "genres": "Action, Drama, Mystery",
    "runtime": "6060",
    "plot": "Captain Jordan Wright's squadron on leave for a wedding in Mexico encounters a murderous cartel. As Jordan tries to lead survivors to safety, war erupts between his squad and the cartel, forcing him into a battle to save his men.",
    "image": "https://m.media-amazon.com/images/M/MV5BZDJiNWQ3NzgtODZlZC00YjljLWJmYWYtMTA4YzExYTcwMGFlXkEyXkFqcGc@._V1_.jpg",
    "imageCaption": "Kiefer Sutherland in Brothers Under Fire (2026)",
    "metascore": "",
    "certificate": "",
    "status": "Released"
  }
]
