[
  {
    "Rank": "1",
    "Show Name": "The Waterfront",
    "IMDb Rating": "7",
    "Link": "https://www.imdb.com/title/tt31216548/"
  },
  {
    "Rank": "2",
    "Show Name": "Dept. Q",
    "IMDb Rating": "8.2",
    "Link": "https://www.imdb.com/title/tt27995114/"
  },
  {
    "Rank": "3",
    "Show Name": "Countdown",
    "IMDb Rating": "6.8",
    "Link": "https://www.imdb.com/title/tt32559610/"
  },
  {
    "Rank": "4",
    "Show Name": "We Were Liars",
    "IMDb Rating": "6.7",
    "Link": "https://www.imdb.com/title/tt3914054/"
  },
  {
    "Rank": "5",
    "Show Name": "Smoke",
    "IMDb Rating": "6.3",
    "Link": "https://www.imdb.com/title/tt24163532/"
  },
  {
    "Rank": "6",
    "Show Name": "MobLand",
    "IMDb Rating": "8.4",
    "Link": "https://www.imdb.com/title/tt31510819/"
  },
  {
    "Rank": "7",
    "Show Name": "Murderbot",
    "IMDb Rating": "7.4",
    "Link": "https://www.imdb.com/title/tt30444310/"
  },
  {
    "Rank": "8",
    "Show Name": "Stick",
    "IMDb Rating": "6.9",
    "Link": "https://www.imdb.com/title/tt31710249/"
  },
  {
    "Rank": "9",
    "Show Name": "Duster",
    "IMDb Rating": "7.3",
    "Link": "https://www.imdb.com/title/tt12160826/"
  },
  {
    "Rank": "10",
    "Show Name": "The Pitt",
    "IMDb Rating": "8.9",
    "Link": "https://www.imdb.com/title/tt31938062/"
  },
  {
    "Rank": "11",
    "Show Name": "Guimi Zhi Zhu",
    "IMDb Rating": "8.9",
    "Link": "https://www.imdb.com/title/tt28618556/"
  },
  {
    "Rank": "12",
    "Show Name": "The Better Sister",
    "IMDb Rating": "7",
    "Link": "https://www.imdb.com/title/tt32260680/"
  },
  {
    "Rank": "13",
    "Show Name": "Dexter: Resurrection",
    "IMDb Rating": "0",
    "Link": "https://www.imdb.com/title/tt33043892/"
  },
  {
    "Rank": "14",
    "Show Name": "Your Friends & Neighbors",
    "IMDb Rating": "7.7",
    "Link": "https://www.imdb.com/title/tt30459041/"
  },
  {
    "Rank": "15",
    "Show Name": "The Terminal List: Dark Wolf",
    "IMDb Rating": "0",
    "Link": "https://www.imdb.com/title/tt26576161/"
  },
  {
    "Rank": "16",
    "Show Name": "Revival",
    "IMDb Rating": "7",
    "Link": "https://www.imdb.com/title/tt13951052/"
  },
  {
    "Rank": "17",
    "Show Name": "Olympo",
    "IMDb Rating": "5.9",
    "Link": "https://www.imdb.com/title/tt33029688/"
  },
  {
    "Rank": "18",
    "Show Name": "Criminal Justice: A Family Matter",
    "IMDb Rating": "7.6",
    "Link": "https://www.imdb.com/title/tt36813889/"
  },
  {
    "Rank": "19",
    "Show Name": "The Studio",
    "IMDb Rating": "8.1",
    "Link": "https://www.imdb.com/title/tt23649128/"
  },
  {
    "Rank": "20",
    "Show Name": "Chespirito: Sin querer queriendo",
    "IMDb Rating": "7.5",
    "Link": "https://www.imdb.com/title/tt34755671/"
  },
  {
    "Rank": "21",
    "Show Name": "Hikaru ga Shinda Natsu",
    "IMDb Rating": "8.2",
    "Link": "https://www.imdb.com/title/tt33028568/"
  },
  {
    "Rank": "22",
    "Show Name": "The Four Seasons",
    "IMDb Rating": "7.2",
    "Link": "https://www.imdb.com/title/tt30826447/"
  },
  {
    "Rank": "23",
    "Show Name": "Daredevil: Born Again",
    "IMDb Rating": "8.1",
    "Link": "https://www.imdb.com/title/tt18923754/"
  },
  {
    "Rank": "24",
    "Show Name": "Paradise",
    "IMDb Rating": "7.9",
    "Link": "https://www.imdb.com/title/tt27444205/"
  },
  {
    "Rank": "25",
    "Show Name": "Good Boy",
    "IMDb Rating": "7.6",
    "Link": "https://www.imdb.com/title/tt32361930/"
  },
  {
    "Rank": "26",
    "Show Name": "Murder Most Puzzling",
    "IMDb Rating": "7",
    "Link": "https://www.imdb.com/title/tt13185754/"
  },
  {
    "Rank": "27",
    "Show Name": "Pokssak Sogatsuda",
    "IMDb Rating": "9.1",
    "Link": "https://www.imdb.com/title/tt26471411/"
  },
  {
    "Rank": "28",
    "Show Name": "Ballard",
    "IMDb Rating": "0",
    "Link": "https://www.imdb.com/title/tt26676904/"
  },
  {
    "Rank": "29",
    "Show Name": "Patience",
    "IMDb Rating": "7.4",
    "Link": "https://www.imdb.com/title/tt31495377/"
  },
  {
    "Rank": "30",
    "Show Name": "El Eternauta",
    "IMDb Rating": "7.3",
    "Link": "https://www.imdb.com/title/tt27740241/"
  },
  {
    "Rank": "31",
    "Show Name": "Ransom Canyon",
    "IMDb Rating": "6.8",
    "Link": "https://www.imdb.com/title/tt28088031/"
  },
  {
    "Rank": "32",
    "Show Name": "Alien: Earth",
    "IMDb Rating": "0",
    "Link": "https://www.imdb.com/title/tt13623632/"
  },
  {
    "Rank": "33",
    "Show Name": "Overcompensating",
    "IMDb Rating": "7.8",
    "Link": "https://www.imdb.com/title/tt23488694/"
  },
  {
    "Rank": "34",
    "Show Name": "Adults",
    "IMDb Rating": "7.4",
    "Link": "https://www.imdb.com/title/tt33049767/"
  },
  {
    "Rank": "35",
    "Show Name": "The Librarians: The Next Chapter",
    "IMDb Rating": "6.3",
    "Link": "https://www.imdb.com/title/tt27799594/"
  },
  {
    "Rank": "36",
    "Show Name": "Death Valley",
    "IMDb Rating": "6.9",
    "Link": "https://www.imdb.com/title/tt32409123/"
  },
  {
    "Rank": "37",
    "Show Name": "Art Detectives",
    "IMDb Rating": "6.9",
    "Link": "https://www.imdb.com/title/tt33045989/"
  },
  {
    "Rank": "38",
    "Show Name": "Head Over Heels",
    "IMDb Rating": "8.7",
    "Link": "https://www.imdb.com/title/tt37146661/"
  },
  {
    "Rank": "39",
    "Show Name": "Gwang-jang",
    "IMDb Rating": "7.5",
    "Link": "https://www.imdb.com/title/tt29650530/"
  },
  {
    "Rank": "40",
    "Show Name": "The Institute",
    "IMDb Rating": "0",
    "Link": "https://www.imdb.com/title/tt10946316/"
  },
  {
    "Rank": "41",
    "Show Name": "This City Is Ours",
    "IMDb Rating": "7.9",
    "Link": "https://www.imdb.com/title/tt31438328/"
  },
  {
    "Rank": "42",
    "Show Name": "Running Point",
    "IMDb Rating": "7.3",
    "Link": "https://www.imdb.com/title/tt14879018/"
  },
  {
    "Rank": "43",
    "Show Name": "Motorheads",
    "IMDb Rating": "7.6",
    "Link": "https://www.imdb.com/title/tt13723084/"
  },
  {
    "Rank": "44",
    "Show Name": "Long Bright River",
    "IMDb Rating": "6.9",
    "Link": "https://www.imdb.com/title/tt8332798/"
  },
  {
    "Rank": "45",
    "Show Name": "Sherlock & Daughter",
    "IMDb Rating": "7",
    "Link": "https://www.imdb.com/title/tt31322085/"
  },
  {
    "Rank": "46",
    "Show Name": "The Black Dagger Brotherhood",
    "IMDb Rating": "7",
    "Link": "https://www.imdb.com/title/tt33095092/"
  },
  {
    "Rank": "47",
    "Show Name": "Mix Tape",
    "IMDb Rating": "7.5",
    "Link": "https://www.imdb.com/title/tt30505625/"
  },
  {
    "Rank": "48",
    "Show Name": "Lazarus",
    "IMDb Rating": "7.1",
    "Link": "https://www.imdb.com/title/tt28454008/"
  },
  {
    "Rank": "49",
    "Show Name": "Tu Bian Ying Xiong X",
    "IMDb Rating": "8.4",
    "Link": "https://www.imdb.com/title/tt23139038/"
  },
  {
    "Rank": "50",
    "Show Name": "Our Unwritten Seoul",
    "IMDb Rating": "8.4",
    "Link": "https://www.imdb.com/title/tt36724865/"
  }
]
